DLICV/__init__.py
DLICV/__main__.py
DLICV/utils.py
dlicv-1.0.6.dist-info/licenses/LICENSE
dlicv-1.0.6.dist-info/METADATA
dlicv-1.0.6.dist-info/WHEEL
dlicv-1.0.6.dist-info/entry_points.txt
dlicv-1.0.6.dist-info/top_level.txt
dlicv-1.0.6.dist-info/RECORD
