Metadata-Version: 2.4
Name: DLICV
Version: 1.0.6
Summary: DLICV - Deep Learning Intra Cranial Volume.
Home-page: https://github.com/CBICA/DLICV/
Download-URL: https://github.com/CBICA/DLICV/
Author: Guray Erus, Vishnu Bashyam, George Aidinis, Alexander Getka, Kyunglok Baik, Wu Di
Author-email: software@cbica.upenn.edu
Maintainer: George Aidinis, Spiros Maggioros, Kyunglok Baik, Alexander Getka
Maintainer-email: aidinisg@pennmedicine.upenn.edu, Spiros.Maggioros@pennmedicine.upenn.edu, kyunglok.baik@pennmedicine.upenn.edu, alexander.getka@pennmedicine.upenn.edu
License: By installing/using DLICV, the user agrees to the following license: See https://www.med.upenn.edu/cbica/software-agreement-non-commercial.html
Keywords: deep learning,image segmentation,semantic segmentation,medical image analysis,medical image segmentation,nnU-Net,nnunet
Classifier: Intended Audience :: Developers
Classifier: Intended Audience :: Science/Research
Classifier: Intended Audience :: Healthcare Industry
Classifier: Programming Language :: Python :: 3
Classifier: Topic :: Scientific/Engineering :: Artificial Intelligence
Classifier: Topic :: Scientific/Engineering :: Image Processing
Classifier: Topic :: Scientific/Engineering :: Medical Science Apps.
Requires-Python: >=3.8
License-File: LICENSE
Requires-Dist: torch==2.3.1
Requires-Dist: numpy==1.26.4
Requires-Dist: nnunetv2==2.5.1
Requires-Dist: acvl_utils==0.2.5
Requires-Dist: blosc2==3.0.0b4
Requires-Dist: argparse
Requires-Dist: huggingface_hub
Dynamic: author
Dynamic: author-email
Dynamic: classifier
Dynamic: description
Dynamic: description-content-type
Dynamic: download-url
Dynamic: home-page
Dynamic: keywords
Dynamic: license
Dynamic: license-file
Dynamic: maintainer
Dynamic: maintainer-email
Dynamic: requires-dist
Dynamic: requires-python
Dynamic: summary
